divide/__init__.py
divide/divide_by_three.py
multiply/__init__.py
multiply/multiply_by_three.py
ptest_test_test_cdtest-1.0.0.dist-info/LICENSE.txt
ptest_test_test_cdtest-1.0.0.dist-info/METADATA
ptest_test_test_cdtest-1.0.0.dist-info/WHEEL
ptest_test_test_cdtest-1.0.0.dist-info/top_level.txt
ptest_test_test_cdtest-1.0.0.dist-info/RECORD
