Metadata-Version: 2.1
Name: ptest-test-test-cdtest
Version: 1.0.0
Summary: A simple Python package
Home-page: https://www.mailbrand.org
Author: chris dean
Author-email: chris.dean@shc.qinetiq.com
Project-URL: Bug Tracker, https://www.mailbrand.org/
Project-URL: repository, https://www.mailbrand.org/
Classifier: Programming Language :: Python :: 3
Classifier: License :: OSI Approved :: MIT License
Classifier: Operating System :: OS Independent
Requires-Python: >=3.6
License-File: LICENSE.txt
